yt_summary/__init__.py
yt_summary/__main__.py
yt_summary/cli/__init__.py
yt_summary/cli/cli.py
yt_summary/cli/errors.py
yt_summary/config.py
yt_summary/extractors/__init__.py
yt_summary/extractors/a
yt_summary/extractors/metadata.py
yt_summary/extractors/transcript.py
yt_summary/llm_config.py
yt_summary/run/__init__.py
yt_summary/run/getters.py
yt_summary/run/runners.py
yt_summary/schemas/__init__.py
yt_summary/schemas/enums.py
yt_summary/schemas/exceptions.py
yt_summary/schemas/models.py
yt_summary/schemas/summary_reponses.py
yt_summary/summarisers/__init__.py
yt_summary/summarisers/base_summariser.py
yt_summary/summarisers/refined_summariser.py
yt_summary/summarisers/simple_summariser.py
yt_summary/summarisers/templates.py
yt_summary/utils/__init__.py
yt_summary/utils/async_helpers.py
yt_summary/utils/misc.py
yt_pls-0.0.1.dist-info/WHEEL
yt_pls-0.0.1.dist-info/entry_points.txt
yt_pls-0.0.1.dist-info/METADATA
yt_pls-0.0.1.dist-info/RECORD
