Metadata-Version: 2.4
Name: yt-pls
Version: 0.0.1
Summary: Youtube Summariser with LlamaIndex
Keywords: youtube,summary,llamaindex,genai
Author: Nelson Ngai
Author-email: Nelson Ngai <nelsonn.xyz@gmail.com>
License-Expression: MIT
Requires-Dist: aiohttp>=3.12.15
Requires-Dist: llama-index>=0.13.2
Requires-Dist: pydantic>=2.11.7
Requires-Dist: pydantic-settings>=2.10.1
Requires-Dist: types-requests>=2.32.4.20250809
Requires-Dist: youtube-transcript-api>=1.2.2
Requires-Dist: llama-index-embeddings-google-genai>=0.3.0 ; extra == 'all'
Requires-Dist: llama-index-llms-google-genai>=0.3.0 ; extra == 'all'
Requires-Dist: llama-index-llms-anthropic>=0.8.5 ; extra == 'all'
Requires-Dist: llama-index-llms-anthropic>=0.8.5 ; extra == 'anthropic'
Requires-Dist: llama-index-embeddings-google-genai>=0.3.0 ; extra == 'google'
Requires-Dist: llama-index-llms-google-genai>=0.3.0 ; extra == 'google'
Requires-Python: >=3.13
Project-URL: Repository, https://github.com/nelnn/yt-pls
Provides-Extra: all
Provides-Extra: anthropic
Provides-Extra: google
